anicli_api/_http.py
anicli_api/_logger.py
anicli_api/base.py
anicli_api/typing.py
anicli_api/player/__init__.py
anicli_api/player/aniboom.py
anicli_api/player/askor.py
anicli_api/player/base.py
anicli_api/player/cdnvideohub.py
anicli_api/player/csst.py
anicli_api/player/dreamcast_chipers.py
anicli_api/player/kodik.py
anicli_api/player/sibnet.py
anicli_api/player/sovetromantica.py
anicli_api/player/sovetromantica_embed.py
anicli_api/player/apis/cdnvideohub.py
anicli_api/player/parsers/__init__.py
anicli_api/player/parsers/aniboom_parser.py
anicli_api/player/parsers/cdnvideohub_parser.py
anicli_api/player/parsers/kodik_parser.py
anicli_api/source/__init__.py
anicli_api/source/anilibme.py
anicli_api/source/anilibria.py
anicli_api/source/animego.py
anicli_api/source/animevost.py
anicli_api/source/dreamcast.py
anicli_api/source/jutsu.py
anicli_api/source/sameband.py
anicli_api/source/yummy_anime.py
anicli_api/source/yummy_anime_org.py
anicli_api/source/apis/__init__.py
anicli_api/source/apis/aniliberty.py
anicli_api/source/apis/animelib_org.py
anicli_api/source/apis/animevost.py
anicli_api/source/apis/dreamerscast.py
anicli_api/source/apis/yummy_anime.py
anicli_api/source/parsers/__init__.py
anicli_api/source/parsers/animego_parser.py
anicli_api/source/parsers/dreamerscast_parser.py
anicli_api/source/parsers/jutsu_parser.py
anicli_api/source/parsers/sameband_parser.py
anicli_api/source/parsers/yummy_anime_org_parser.py
anicli_api/tools/__init__.py
anicli_api/tools/cookies.py
anicli_api/tools/dummy_cli.py
anicli_api/tools/helpers.py
anicli_api/tools/m3u.py
anicli_api-0.8.10.dist-info/METADATA
anicli_api-0.8.10.dist-info/WHEEL
anicli_api-0.8.10.dist-info/licenses/LICENSE
anicli_api-0.8.10.dist-info/RECORD
