Metadata-Version: 2.4
Name: anicli_api
Version: 0.8.10
Summary: Anime extractors api implementation
Project-URL: Issues, https://github.com/vypivshiy/anicli-api/issues
Project-URL: Source, https://github.com/vypivshiy/anicli-api
Project-URL: Cli app, https://github.com/vypivshiy/ani-cli-ru
License-Expression: MIT
License-File: LICENSE
Keywords: anime,api,asyncio,dev,httpx,parser,ru,russia
Classifier: Environment :: Console
Classifier: Intended Audience :: Developers
Classifier: License :: OSI Approved :: MIT License
Classifier: Programming Language :: Python :: 3.9
Classifier: Programming Language :: Python :: 3.10
Classifier: Programming Language :: Python :: 3.11
Classifier: Programming Language :: Python :: 3.12
Classifier: Programming Language :: Python :: 3.13
Classifier: Topic :: Software Development :: Libraries :: Python Modules
Classifier: Topic :: Software Development :: Quality Assurance
Classifier: Typing :: Typed
Requires-Python: >=3.9
Requires-Dist: attrs>=25.3.0
Requires-Dist: cssselect>=1.2.0
Requires-Dist: httpx[http2,socks]>=0.28.1
Requires-Dist: lxml>=5.3.1
Requires-Dist: typing-extensions>=4.12.2; python_full_version < '3.11'
